johnnydep/__init__.py
johnnydep/__main__.py
johnnydep/cli.py
johnnydep/compat.py
johnnydep/dot.py
johnnydep/env_check.py
johnnydep/lib.py
johnnydep/logs.py
johnnydep/pipper.py
johnnydep/util.py
johnnydep-1.20.6.dist-info/LICENSE
johnnydep-1.20.6.dist-info/METADATA
johnnydep-1.20.6.dist-info/WHEEL
johnnydep-1.20.6.dist-info/entry_points.txt
johnnydep-1.20.6.dist-info/top_level.txt
johnnydep-1.20.6.dist-info/RECORD
