Metadata-Version: 2.1
Name: johnnydep
Version: 1.20.6
Summary: Display dependency tree of Python distribution
Home-page: https://github.com/wimglenn/johnnydep
Author: Wim Glenn
Author-email: hey@wimglenn.com
License: MIT
License-File: LICENSE
Requires-Dist: anytree
Requires-Dist: structlog
Requires-Dist: tabulate
Requires-Dist: wimpy
Requires-Dist: cachetools
Requires-Dist: oyaml
Requires-Dist: toml
Requires-Dist: pip
Requires-Dist: packaging !=22,>=17
Requires-Dist: wheel >=0.32.0
Requires-Dist: importlib-metadata ; python_version < "3.10"
Requires-Dist: pyblake2 ; python_version < "3.6"
Requires-Dist: colorama ; python_version < "3.7" or platform_system == "Windows"
Requires-Dist: zipfile38 ; python_version < "3.8" and python_version != "2.7"
Requires-Dist: zipfile39 ; python_version == "2.7"
